[
  {
    "id": "1",
    "name": "Allen Raymond",
    "email": "nulla.ante@vestibul.co.uk",
    "phone": "(992) 914-3792"
  },
  {
    "id": "2",
    "name": "Chaim Lewis",
    "email": "dui.in@egetlacus.ca",
    "phone": "(294) 840-6685"
  },
  {
    "id": "4",
    "name": "Wylie Pope",
    "email": "est@utquamvel.net",
    "phone": "(692) 802-2949"
  },
  {
    "id": "5",
    "name": "Cyrus Jackson",
    "email": "nibh@semsempererat.com",
    "phone": "(501) 472-5218"
  },
  {
    "id": "6",
    "name": "Abbot Franks",
    "email": "scelerisque@magnis.org",
    "phone": "(186) 568-3720"
  },
  {
    "id": "7",
    "name": "Reuben Henry",
    "email": "pharetra.ut@dictum.co.uk",
    "phone": "(715) 598-5792"
  },
  {
    "id": "8",
    "name": "Simon Morton",
    "email": "dui.Fusce.diam@Donec.com",
    "phone": "(233) 738-2360"
  },
  {
    "id": "9",
    "name": "Thomas Lucas",
    "email": "nec@Nulla.com",
    "phone": "(704) 398-7993"
  },
  {
    "id": "10",
    "name": "Alec Howard",
    "email": "Donec.elementum@scelerisquescelerisquedui.net",
    "phone": "(748) 206-2688"
  },
  {
    "id": "00xMN8NVCI8BB6iGM6ui5",
    "name": "Mango",
    "email": "mango@gmail.com",
    "phone": "322-22-22"
  },
  {
    "id": "slvqK0d4MaRv_DBl_Ti_1",
    "name": "Mango",
    "email": "mango@gmail.com",
    "phone": "322-22-22"
  },
  {
    "id": "dxc6dCyAxHDjHvsjSV6qR",
    "name": "Mango",
    "email": "mango@gmail.com",
    "phone": "322-22-22"
  },
  {
    "id": "IXK7k_fvrEqZ5nnBvM12V",
    "name": "Mango",
    "email": "mango@gmail.com",
    "phone": "322-22-22"
  },
  {
    "id": "MkIgm6-eMBwciGOHkm9hg",
    "name": "Mango",
    "email": "mango@gmail.com",
    "phone": "322-22-22"
  },
  {
    "id": "WEAkHE1BrvDzI_j6WHjdr",
    "name": "Mango",
    "email": "mango@gmail.com",
    "phone": "322-22-22"
  },
  {
    "id": "hPWJmloySTU4paCWG0GBq",
    "name": "Mango",
    "email": "mango@gmail.com",
    "phone": "322-22-22"
  },
  {
    "id": "iOrsq2n8E7K28mZc5EoDN",
    "name": "Mango",
    "email": "mango@gmail.com",
    "phone": "322-22-22"
  },
  {
    "id": "BYU0CASGbL1hEHaUQ8JHS",
    "name": "Mango",
    "email": "mango@gmail.com",
    "phone": "322-22-22"
  },
  {
    "id": "VJ9ZyQgCYft5EcD-V0SIG",
    "name": "Mango",
    "email": "mango@gmail.com",
    "phone": "322-22-22"
  },
  {
    "id": "rcx0-CYsTOdz-gusQ1FiV",
    "name": "Mango",
    "email": "mango@gmail.com",
    "phone": "322-22-22"
  },
  {
    "id": "It0-igfjEdo_mHmrvAzhk",
    "name": "Mango",
    "email": "mango@gmail.com",
    "phone": "322-22-22"
  },
  {
    "id": "VcVidp3M9kEqhKE5Ei0Vn",
    "name": "Mango",
    "email": "mango@gmail.com",
    "phone": "322-22-22"
  },
  {
    "id": "MsKe1GFuiCVEAlCZ1ylaD",
    "name": "Mango",
    "email": "mango@gmail.com",
    "phone": "322-22-22"
  },
  {
    "id": "KZ76ZO2rXY68kq-UqRsKj",
    "name": "Mango",
    "email": "mango@gmail.com",
    "phone": "322-22-22"
  },
  {
    "id": "vWDiJPcjsYhixO_yF6NM-",
    "name": "Mango",
    "email": "mango@gmail.com",
    "phone": "322-22-22"
  },
  {
    "id": "5brnURFymq0OZJI_pEvZj",
    "name": "Mango",
    "email": "mango@gmail.com",
    "phone": "322-22-22"
  },
  {
    "id": "Oj2eZETKvzHKzyzeR_Y_3",
    "name": "Mango",
    "email": "mango@gmail.com",
    "phone": "322-22-22"
  },
  {
    "id": "EckTPMrmVgW0NSDVJlmDo",
    "name": "Mango",
    "email": "mango@gmail.com",
    "phone": "322-22-22"
  },
  {
    "id": "z6CwxZNUgeh5nKKlAzMyq",
    "name": "Mango",
    "email": "mango@gmail.com",
    "phone": "322-22-22"
  },
  {
    "id": "SZDiCClkgMHbvfDSdZ9Pl",
    "name": "Mango",
    "email": "mango@gmail.com",
    "phone": "322-22-22"
  },
  {
    "id": "HgDLaVWiwhXPTcINPMrdL",
    "name": "Mango",
    "email": "mango@gmail.com",
    "phone": "322-22-22"
  },
  {
    "id": "PyiG4M-bNW1YvsKjt6hFw",
    "name": "Mango",
    "email": "mango@gmail.com",
    "phone": "322-22-22"
  },
  {
    "id": "nPM9d5PkHjz5Euum_VIAb",
    "name": "Mango",
    "email": "mango@gmail.com",
    "phone": "322-22-22"
  },
  {
    "id": "sKD9jZ5-Aogxss0x8tC1Y",
    "name": "Mango",
    "email": "mango@gmail.com",
    "phone": "322-22-22"
  },
  {
    "id": "qVdEYeMrW0DAbBL8pPeCn",
    "name": "Mango",
    "email": "mango@gmail.com",
    "phone": "322-22-22"
  },
  {
    "id": "Bh9lY9Yczumh5UhS_0ex6",
    "name": "Mango",
    "email": "mango@gmail.com",
    "phone": "322-22-22"
  },
  {
    "id": "SD2_RLh-6E-bJEZPiVXmQ",
    "name": "Mango",
    "email": "mango@gmail.com",
    "phone": "322-22-22"
  },
  {
    "id": "FOCCoSlB8wc0jHOhEX5Qo",
    "name": "Mango",
    "email": "mango@gmail.com",
    "phone": "322-22-22"
  },
  {
    "id": "E6ZIFZ5Ee0sX_bay-yUbp",
    "name": "Mango",
    "email": "mango@gmail.com",
    "phone": "322-22-22"
  },
  {
    "id": "kFe8bjxfhi9GatbPvfHu4",
    "name": "Mango",
    "email": "mango@gmail.com",
    "phone": "322-22-22"
  },
  {
    "id": "WGJNRYLggwob6tckUwoDt",
    "name": "Mango",
    "email": "mango@gmail.com",
    "phone": "322-22-22"
  },
  {
    "id": "cs6jqDzv4hEDdxyl65J0G",
    "name": "Mango",
    "email": "mango@gmail.com",
    "phone": "322-22-22"
  },
  {
    "id": "-CfDQLcVb4WTaW84smAim",
    "name": "Mango",
    "email": "mango@gmail.com",
    "phone": "322-22-22"
  },
  {
    "id": "S9RvNDqXEIFFExZdrsyul",
    "name": "Mango",
    "email": "mango@gmail.com",
    "phone": "322-22-22"
  },
  {
    "id": "kLe2cDUeKkqtINrLqOT-X",
    "name": "Mango",
    "email": "mango@gmail.com",
    "phone": "322-22-22"
  },
  {
    "id": "q0YlsD46omTP-BCsEJHh9",
    "name": "Mango",
    "email": "mango@gmail.com",
    "phone": "322-22-22"
  },
  {
    "id": "yVpxZ7n2nB1p8Vtoq7_x2",
    "name": "Mango",
    "email": "mango@gmail.com",
    "phone": "322-22-22"
  },
  {
    "id": "q80dGYw50cw8nKUiv9M0r",
    "name": "Mango",
    "email": "mango@gmail.com",
    "phone": "322-22-22"
  },
  {
    "id": "e4P7cmgeYNP55yA-iKvVs",
    "name": "Mango",
    "email": "mango@gmail.com",
    "phone": "322-22-22"
  },
  {
    "id": "AehDY6lcGyW7ntsec5ViM",
    "name": "Mango",
    "email": "mango@gmail.com",
    "phone": "322-22-22"
  },
  {
    "id": "oSR66_zIn-UEmR-xpUL5z",
    "name": "Mango",
    "email": "mango@gmail.com",
    "phone": "322-22-22"
  },
  {
    "id": "sgYkmW9IMpBsOWP-MocbO",
    "name": "Mango",
    "email": "mango@gmail.com",
    "phone": "322-22-22"
  },
  {
    "id": "GqUeO2rmo8aVMPz_HIAye",
    "name": "Mango",
    "email": "mango@gmail.com",
    "phone": "322-22-22"
  },
  {
    "id": "bETk1FRYigSmwfguZFDnz",
    "name": "Mango",
    "email": "mango@gmail.com",
    "phone": "322-22-22"
  },
  {
    "id": "RDZ7ROWikPZArcPEoqgP2",
    "name": "Mango",
    "email": "mango@gmail.com",
    "phone": "322-22-22"
  },
  {
    "id": "SJys8l71zMPTWCpAwYWKn",
    "name": "Mango",
    "email": "mango@gmail.com",
    "phone": "322-22-22"
  },
  {
    "id": "-NcBE71wb8ZixKOdkMIDw",
    "name": "Mango",
    "email": "mango@gmail.com",
    "phone": "322-22-22"
  },
  {
    "id": "tscqTn4Jrbg4Y9J04GdUx",
    "name": "Mango",
    "email": "mango@gmail.com",
    "phone": "322-22-22"
  },
  {
    "id": "fcthla3crsS6JHGPrFY1A",
    "name": "Mango",
    "email": "mango@gmail.com",
    "phone": "322-22-22"
  },
  {
    "id": "L_X12GPh66nMuDLZb8aXq",
    "name": "Mango",
    "email": "mango@gmail.com",
    "phone": "322-22-22"
  },
  {
    "id": "hcGEEe7zk_R1gDpu9d2in",
    "name": "Mango",
    "email": "mango@gmail.com",
    "phone": "322-22-22"
  },
  {
    "id": "bG7fCe_gbS_lv6kL7dQg7",
    "name": "Mango",
    "email": "mango@gmail.com",
    "phone": "322-22-22"
  },
  {
    "id": "hVdzmZEQj-eaWTzm787GC",
    "name": "Mango",
    "email": "mango@gmail.com",
    "phone": "322-22-22"
  },
  {
    "id": "p3Ax2y9g37nZqR14INJ0r",
    "name": "Mango",
    "email": "mango@gmail.com",
    "phone": "322-22-22"
  },
  {
    "id": "BEUP_HTMstETGTgURZUsU",
    "name": "Mango",
    "email": "mango@gmail.com",
    "phone": "322-22-22"
  },
  {
    "id": "vt1LAuDSNAgRbZQeDHIEV",
    "name": "Mango",
    "email": "mango@gmail.com",
    "phone": "322-22-22"
  },
  {
    "id": "LZGsE16tcDU3dYteiOCH4",
    "name": "Mango",
    "email": "mango@gmail.com",
    "phone": "322-22-22"
  },
  {
    "id": "0F1rpjkcurE-udU1EFv1H",
    "name": "Mango",
    "email": "mango@gmail.com",
    "phone": "322-22-22"
  },
  {
    "id": "NijhxmsENbP589hZiwlM_",
    "name": "Mango",
    "email": "mango@gmail.com",
    "phone": "322-22-22"
  },
  {
    "id": "qbfhejUtD4FCPwoq1H6wD",
    "name": "Mango",
    "email": "mango@gmail.com",
    "phone": "322-22-22"
  },
  {
    "id": "65LN76Sx_TFLZVmU38YKi",
    "name": "Mango",
    "email": "mango@gmail.com",
    "phone": "322-22-22"
  },
  {
    "id": "SkwwbkNND6pHbh9E81LRV",
    "name": "Mango",
    "email": "mango@gmail.com",
    "phone": "322-22-22"
  },
  {
    "id": "7_9QjXYyZFMEsTdi1q4xS",
    "name": "Mango",
    "email": "mango@gmail.com",
    "phone": "322-22-22"
  },
  {
    "id": "3cC7rzzceg9J36vGu72PP",
    "name": "Mango",
    "email": "mango@gmail.com",
    "phone": "322-22-22"
  },
  {
    "id": "oWn-JCqzWIcHeYWMkxCTP",
    "name": "Mango",
    "email": "mango@gmail.com",
    "phone": "322-22-22"
  },
  {
    "id": "ntR_-b4D0p2_XhTL5gePP",
    "name": "Mango",
    "email": "mango@gmail.com",
    "phone": "322-22-22"
  },
  {
    "id": "TOPtfTE_CPTJWgkcO1jMp",
    "name": "Mango",
    "email": "mango@gmail.com",
    "phone": "322-22-22"
  },
  {
    "id": "Am0kDEOrxfteaWVUalwgh",
    "name": "Mango",
    "email": "mango@gmail.com",
    "phone": "322-22-22"
  },
  {
    "id": "wt2q8u3shjsZL7XJur1bA",
    "name": "Mango",
    "email": "mango@gmail.com",
    "phone": "322-22-22"
  },
  {
    "id": "whSikRkPQgcm8RDSsWXnN",
    "name": "Mango",
    "email": "mango@gmail.com",
    "phone": "322-22-22"
  },
  {
    "id": "5XwvEWISqmE2fWgHnxdUD",
    "name": "Mango",
    "email": "mango@gmail.com",
    "phone": "322-22-22"
  },
  {
    "id": "CkXBqCDRloxGCCH8qvTlJ",
    "name": "Mango",
    "email": "mango@gmail.com",
    "phone": "322-22-22"
  },
  {
    "id": "9amm8iNgP0136bN_rCK7u",
    "name": "Mango",
    "email": "mango@gmail.com",
    "phone": "322-22-22"
  },
  {
    "id": "nWeIKDQwumniNjLxt1spm",
    "name": "Mango",
    "email": "mango@gmail.com",
    "phone": "322-22-22"
  },
  {
    "id": "wsmpYQyix2nZ1q2wx_zFr",
    "name": "Mango",
    "email": "mango@gmail.com",
    "phone": "322-22-22"
  },
  {
    "id": "x3S28ZBljB8R1aHpvV4Ue",
    "name": "Mango",
    "email": "mango@gmail.com",
    "phone": "322-22-22"
  },
  {
    "id": "RcKGSHgfhdoKoj-aF8cH1",
    "name": "Mango",
    "email": "mango@gmail.com",
    "phone": "322-22-22"
  },
  {
    "id": "4Jv_tDH3osKIcoHlQQmtb",
    "name": "Mango",
    "email": "mango@gmail.com",
    "phone": "322-22-22"
  },
  {
    "id": "FtEFQF73ooWj20DBniAJF",
    "name": "Mango",
    "email": "mango@gmail.com",
    "phone": "322-22-22"
  },
  {
    "id": "KWWlNA1e4xvYHIvDxSUWy",
    "name": "Mango",
    "email": "mango@gmail.com",
    "phone": "322-22-22"
  },
  {
    "id": "qnE-flVJY7WyrsONjhh21",
    "name": "Mango",
    "email": "mango@gmail.com",
    "phone": "322-22-22"
  },
  {
    "id": "CGsh5iAMtTEq-ZAmVyhQ8",
    "name": "Mango",
    "email": "mango@gmail.com",
    "phone": "322-22-22"
  },
  {
    "id": "vm5EBqJSYWeh3MO_nzj46",
    "name": "Mango",
    "email": "mango@gmail.com",
    "phone": "322-22-22"
  },
  {
    "id": "mu4jrTquUr8c1g1sbpQw6",
    "name": "Mango",
    "email": "mango@gmail.com",
    "phone": "322-22-22"
  },
  {
    "id": "E3e9mITxU_MSznmQ7Cv0z",
    "name": "Mango",
    "email": "mango@gmail.com",
    "phone": "322-22-22"
  },
  {
    "id": "NrkfJyQXmvLBE2feuIx85",
    "name": "Mango",
    "email": "mango@gmail.com",
    "phone": "322-22-22"
  },
  {
    "id": "2mfk-pIfr7VU7xQhohwwu",
    "name": "Mango",
    "email": "mango@gmail.com",
    "phone": "322-22-22"
  },
  {
    "id": "tvy03xIbYIs_ZCy2qbsba",
    "name": "Mango",
    "email": "mango@gmail.com",
    "phone": "322-22-22"
  },
  {
    "id": "5L6KqIz_oVXitflHq8PGv",
    "name": "Mango",
    "email": "mango@gmail.com",
    "phone": "322-22-22"
  },
  {
    "id": "KoCjspvT0HXWhwQ-o_yED",
    "name": "Mango",
    "email": "mango@gmail.com",
    "phone": "322-22-22"
  },
  {
    "id": "5lqQ7RjaGGwNK8MjvIx6X",
    "name": "Mango",
    "email": "mango@gmail.com",
    "phone": "322-22-22"
  },
  {
    "id": "_bnYyfjUjDDJP-CcurPd8",
    "name": "Mango",
    "email": "mango@gmail.com",
    "phone": "322-22-22"
  },
  {
    "id": "aUhYvMUADPiauuY32r9al",
    "name": "Mango",
    "email": "mango@gmail.com",
    "phone": "322-22-22"
  },
  {
    "id": "lB_PwDb2X5tujV97NXM3x",
    "name": "Mango",
    "email": "mango@gmail.com",
    "phone": "322-22-22"
  },
  {
    "id": "z57QG9LTBZ5r6wfug-Rlh",
    "name": "Mango",
    "email": "mango@gmail.com",
    "phone": "322-22-22"
  },
  {
    "id": "srHWDi0ghK0LKBYFkpnjo",
    "name": "Mango",
    "email": "mango@gmail.com",
    "phone": "322-22-22"
  },
  {
    "id": "8CrWWqexr4_Sde6TByGz4",
    "name": "Mango",
    "email": "mango@gmail.com",
    "phone": "322-22-22"
  },
  {
    "id": "EFFV2bM3-7p5bTSMW4KAX",
    "name": "Mango",
    "email": "mango@gmail.com",
    "phone": "322-22-22"
  },
  {
    "id": "KVaxY5ABY-FFQQb29XS3A",
    "name": "Mango",
    "email": "mango@gmail.com",
    "phone": "322-22-22"
  },
  {
    "id": "Z2BwAcsNClxVm6D6nIDlM",
    "name": "Mango",
    "email": "mango@gmail.com",
    "phone": "322-22-22"
  },
  {
    "id": "pq8IOTB1LUzGlElFajn5T",
    "name": "Mango",
    "email": "mango@gmail.com",
    "phone": "322-22-22"
  },
  {
    "id": "00vhMF863pjhVHQoMn7m0",
    "name": "Mango",
    "email": "mango@gmail.com",
    "phone": "322-22-22"
  },
  {
    "id": "YWFKJrmqU1Puj7cHn-Q5m",
    "name": "Mango",
    "email": "mango@gmail.com",
    "phone": "322-22-22"
  },
  {
    "id": "8DegEHm_GR8rrKbf1u97J",
    "name": "Mango",
    "email": "mango@gmail.com",
    "phone": "322-22-22"
  },
  {
    "id": "vZ46nhPvKM_E2cQxEIaL9",
    "name": "Mango",
    "email": "mango@gmail.com",
    "phone": "322-22-22"
  },
  {
    "id": "KXR2_ZBb2837PJmBdoUPJ",
    "name": "Mango",
    "email": "mango@gmail.com",
    "phone": "322-22-22"
  },
  {
    "id": "rcU0tLnlKY1p_IMwZFYrg",
    "name": "Mango",
    "email": "mango@gmail.com",
    "phone": "322-22-22"
  },
  {
    "id": "acza3GJCw9EtMlyE_YKt6",
    "name": "Mango",
    "email": "mango@gmail.com",
    "phone": "322-22-22"
  },
  {
    "id": "_734V1Ec2biYTww2nNMMC",
    "name": "Mango",
    "email": "mango@gmail.com",
    "phone": "322-22-22"
  },
  {
    "id": "N6B0RGxnpU7a-ZSUK_0wH",
    "name": "Mango",
    "email": "mango@gmail.com",
    "phone": "322-22-22"
  },
  {
    "id": "_k8QF9Ld7l6p4rkNI9wMD",
    "name": "Mango",
    "email": "mango@gmail.com",
    "phone": "322-22-22"
  },
  {
    "id": "LxSi0761dM14fCOMforXM",
    "name": "Mango",
    "email": "mango@gmail.com",
    "phone": "322-22-22"
  },
  {
    "id": "X1mxnDppOtvFX3dMvc34n",
    "name": "Mango",
    "email": "mango@gmail.com",
    "phone": "322-22-22"
  },
  {
    "id": "JA84Yn9SmNZNDWtpbq82m",
    "name": "Mango",
    "email": "mango@gmail.com",
    "phone": "322-22-22"
  },
  {
    "id": "ESNvkpP8wsGw7K4b6mqQR",
    "name": "Mango",
    "email": "mango@gmail.com",
    "phone": "322-22-22"
  },
  {
    "id": "4HZV73_roc46VHbP0Y306",
    "name": "Mango",
    "email": "mango@gmail.com",
    "phone": "322-22-22"
  }
]